gwsa/__init__.py
gwsa/__main__.py
gwsa/base.py
gwsa/fetch.py
gwsa/rebase.py
gwsa/status.py
tests/__init__.py
tests/misc.py
tests/test_fetch.py
tests/test_status.py
gwsa-1.1.3.dist-info/LICENSE
gwsa-1.1.3.dist-info/METADATA
gwsa-1.1.3.dist-info/WHEEL
gwsa-1.1.3.dist-info/entry_points.txt
gwsa-1.1.3.dist-info/top_level.txt
gwsa-1.1.3.dist-info/RECORD
