Metadata-Version: 2.1
Name: gwsa
Version: 1.1.3
Summary: git workspace automation
Home-page: https://gitlab.com/aanatoly/gwsa
Author: Anatoly Asviyan
Author-email: aanatoly@gmail.com
License: GPLv2
Platform: UNKNOWN
Classifier: Development Status :: 4 - Beta
Classifier: Environment :: Console
Classifier: Intended Audience :: Developers
Classifier: License :: OSI Approved :: GNU General Public License v2 (GPLv2)
Classifier: Operating System :: POSIX
Classifier: Programming Language :: Python :: 2.7
Classifier: Topic :: Software Development :: Version Control
Requires-Dist: gitpython
Requires-Dist: blessed
Provides-Extra: dev
Requires-Dist: tox ; extra == 'dev'
Requires-Dist: cmarkgfm ; extra == 'dev'
Requires-Dist: twine ; extra == 'dev'
